<?xml version="1.0" encoding="UTF-8"?>
<!DOCTYPE hibernate-mapping PUBLIC "-//Hibernate/Hibernate Mapping DTD 3.0//EN" "http://hibernate.sourceforge.net/hibernate-mapping-3.0.dtd">
<!-- 
    Mapping file autogenerated by MyEclipse Persistence Tools
-->
<hibernate-mapping>
  <class name="com.viettel.im.database.BO.SaleServicesStock" table="SALE_SERVICES_STOCK">
    <composite-id class="com.viettel.im.database.BO.SaleServicesStockId" name="id">
      <key-property name="saleServicesModelId" type="java.lang.Long">
        <column name="SALE_SERVICES_MODEL_ID" precision="10" scale="0"/>
      </key-property>
      <key-property name="shopId" type="java.lang.Long">
        <column name="SHOP_ID" precision="10" scale="0"/>
      </key-property>
    </composite-id>
    <property name="shopCode" type="java.lang.String">
      <column length="40" name="SHOP_CODE"/>
    </property>
  </class>
</hibernate-mapping>
